<?xml version="1.0" encoding="UTF-8" standalone="yes"?>
<servico>
    <titulo>Transferência de Arma de Fogo</titulo>
    <descricao>Documento que autoriza a transferência de propriedade da arma de fogo entre particulares. Para o
        transporte da arma de fogo é necessária a apresentação de guia de trânsito (ver serviço Guia de Trânsito).

        ATENÇÃO: A venda/doação e a consequente entrega da arma de fogo somente deve ser realizada após a autorização de
        transferência concedida pela Polícia Federal, tendo em vista a possibilidade de indeferimento do pedido por não
        atendimento aos requisitos legais ou regulamentares. A transferência antecipada da arma sem autorização pode
        caracterizar o crime do porte ilegal de arma.
    </descricao>
    <requisitos/>
    <etapas></etapas>
    <canaisPrestacaoServico>
        <canalPrestacaoServico>
            <tipoCanalPrestacaoServico>
                <titulo>Presencial</titulo>
            </tipoCanalPrestacaoServico>
            <descricao>Dirigir-se a uma das unidade da Polícia Federal munido de requerimento preenchido e da
                documentação necessária (vide "Localização das unidades").
            </descricao>
            <url></url>
        </canalPrestacaoServico>
    </canaisPrestacaoServico>
    <taxa></taxa>
    <informacoesUteis>
        <informacaoUtil>
            <tipoInformacaoUtil>
                <titulo>Mais informações</titulo>
            </tipoInformacaoUtil>
            <descricao>Documentação necessária para os cargos definidos no artigo 28 da Lei 10.826/03.</descricao>
            <url>http://www.dpf.gov.br/servicos/armas/tranferencia-de-arma-de-fogo</url>
        </informacaoUtil>
        <informacaoUtil>
            <tipoInformacaoUtil>
                <titulo>Formulários</titulo>
            </tipoInformacaoUtil>
            <descricao>Formulário de Requerimento SINARM.</descricao>
            <url>http://www.dpf.gov.br/servicos/armas/form-sinarm</url>
        </informacaoUtil>
        <informacaoUtil>
            <tipoInformacaoUtil>
                <titulo>Outros</titulo>
            </tipoInformacaoUtil>
            <descricao>Forma de obtenção das certidões criminais negativas em cada localidade.</descricao>
            <url>http://www.dpf.gov.br/servicos/armas/anexos/certidoes-criminais-negativas</url>
        </informacaoUtil>
        <informacaoUtil>
            <tipoInformacaoUtil>
                <titulo>Localização das unidades</titulo>
            </tipoInformacaoUtil>
            <descricao>Endereços de todas as unidades da Polícia Federal no país.</descricao>
            <url>http://www.dpf.gov.br/institucional/pf-pelo-brasil/</url>
        </informacaoUtil>
        <informacaoUtil>
            <tipoInformacaoUtil>
                <titulo>Telefone</titulo>
            </tipoInformacaoUtil>
            <descricao>Mais informações: 194</descricao>
            <url></url>
        </informacaoUtil>
        <informacaoUtil>
            <tipoInformacaoUtil>
                <titulo>Outros</titulo>
            </tipoInformacaoUtil>
            <descricao>Lei 10.826/03</descricao>
            <url>http://www.planalto.gov.br/ccivil_03/leis/2003/l10.826.htm</url>
        </informacaoUtil>
        <informacaoUtil>
            <tipoInformacaoUtil>
                <titulo>Serviços relacionados</titulo>
            </tipoInformacaoUtil>
            <descricao>Comunicação de ocorrências envolvendo Arma de Fogo</descricao>
            <url>http://www.dpf.gov.br/servicos/armas/comunicacao-de-ocorrencias</url>
        </informacaoUtil>
        <informacaoUtil>
            <tipoInformacaoUtil>
                <titulo>Mais informações</titulo>
            </tipoInformacaoUtil>
            <descricao>Sobre Armas de Fogo</descricao>
            <url>http://www.dpf.gov.br/servicos/armas/</url>
        </informacaoUtil>
    </informacoesUteis>
    <compromissosAtendimento></compromissosAtendimento>
    <legislacoes></legislacoes>
    <palavrasChave></palavrasChave>
    <orgaoResponsavel>
        <titulo>Ministério da Justiça- MJ</titulo>
    </orgaoResponsavel>
    <orgaoPrestador>
        <titulo>Departamento de Polícia Federal</titulo>
        <endereco></endereco>
        <telefone></telefone>
    </orgaoPrestador>
    <publicosAlvo>
        <publicoAlvo>
            <titulo>Serviços aos cidadãos</titulo>
            <linhasDaViva>
                <linhaDaVida>
                    <titulo>Prestando serviço militar</titulo>
                    <eventoslinhaDaVida>
                        <eventolinhaDaVida>
                            <titulo>Licenças</titulo>
                        </eventolinhaDaVida>
                    </eventoslinhaDaVida>
                </linhaDaVida>
            </linhasDaViva>
        </publicoAlvo>
    </publicosAlvo>
    <areasInteresse>
        <area>
            <titulo>Segurança e Ordem Pública</titulo>
        </area>
    </areasInteresse>
</servico>